octostudio/__init__.py
octostudio/microblocks.py
octostudio/scratch.py
octostudio/snap.py
octostudio-0.4.2.dist-info/METADATA
octostudio-0.4.2.dist-info/WHEEL
octostudio-0.4.2.dist-info/entry_points.txt
octostudio-0.4.2.dist-info/RECORD
