Metadata-Version: 2.1
Name: octostudio
Version: 0.4.2
Summary: 
Author: wwj718
Author-email: wuwenjie718@gmail.com
Requires-Python: >=3.10,<3.13
Classifier: Programming Language :: Python :: 3
Classifier: Programming Language :: Python :: 3.10
Classifier: Programming Language :: Python :: 3.11
Requires-Dist: bleak (>=0.21.1,<0.22.0)
Requires-Dist: microblocks-wifi-radio (>=0.4.0,<0.5.0)
